Metadata-Version: 2.1
Name: tabl
Version: 1.2.3
Summary: Lightweight, intuitive and fast data-tables. Forked from github.com/BastiaanBergman/tabel
Home-page: https://github.com/javadba/tabl
Author: Stephen Boesch
Author-email: javadba@gmail.com
License: MIT
Project-URL: Documentation, https://tabl.readthedocs.io/en/stable/
Project-URL: Source Code, https://github.com/javadba/tabl
Keywords: data table
Platform: UNKNOWN
Classifier: Programming Language :: Python :: 3.8
Classifier: License :: OSI Approved :: MIT License
Classifier: Operating System :: OS Independent
Requires-Python: >=3.8
